fastapi_mqtt/__init__.py
fastapi_mqtt/config.py
fastapi_mqtt/fastmqtt.py
fastapi_mqtt/handlers.py
fastapi_mqtt/py.typed
fastapi_mqtt-2.1.0.dist-info/LICENSE
fastapi_mqtt-2.1.0.dist-info/METADATA
fastapi_mqtt-2.1.0.dist-info/WHEEL
fastapi_mqtt-2.1.0.dist-info/RECORD
