Metadata-Version: 2.1
Name: fastapi-mqtt
Version: 2.1.0
Summary: fastapi-mqtt is extension for MQTT protocol
Home-page: https://github.com/sabuhish/fastapi-mqtt
License: MIT
Author: sabuhish
Author-email: sabuhi.shukurov@gmail.com
Requires-Python: >=3.7,<4.0
Classifier: Intended Audience :: Developers
Classifier: License :: OSI Approved :: MIT License
Classifier: Operating System :: OS Independent
Classifier: Programming Language :: Python
Classifier: Programming Language :: Python :: 3
Classifier: Programming Language :: Python :: 3.7
Classifier: Programming Language :: Python :: 3.8
Classifier: Programming Language :: Python :: 3.9
Classifier: Programming Language :: Python :: 3.10
Classifier: Programming Language :: Python :: 3.11
Classifier: Programming Language :: Python :: 3.12
Classifier: Programming Language :: Python :: 3 :: Only
Requires-Dist: fastapi (>=0.103)
Requires-Dist: gmqtt (>=0.6.11)
Requires-Dist: pydantic (>=2.3.0)
Requires-Dist: uvicorn (>=0.19.0)
Project-URL: Repository, https://github.com/sabuhish/fastapi-mqtt
